blueye/protocol/__init__.py
blueye/protocol/exceptions.py
blueye/protocol/protos.py
blueye/protocol/types/__init__.py
blueye/protocol/types/aquatroll.py
blueye/protocol/types/control.py
blueye/protocol/types/message_formats.py
blueye/protocol/types/mission_planning.py
blueye/protocol/types/req_rep.py
blueye/protocol/types/telemetry.py
blueye_protocol-3.2.0.dist-info/licenses/LICENSE
blueye_protocol-3.2.0.dist-info/METADATA
blueye_protocol-3.2.0.dist-info/WHEEL
blueye_protocol-3.2.0.dist-info/top_level.txt
blueye_protocol-3.2.0.dist-info/RECORD
