Metadata-Version: 2.4
Name: blueye.protocol
Version: 3.2.0
Summary: Python protocol definition for the Blueye drones
Author-email: Blueye Robotics <contact@blueye.no>
License:                    GNU LESSER GENERAL PUBLIC LICENSE
Project-URL: Homepage, https://www.blueyerobotics.com
Project-URL: Repository, https://github.com/blueye-robotics/blueye.protocol
Keywords: Blueye,Robotics,Protocol
Requires-Python: <4,>=3.10
License-File: LICENSE
Requires-Dist: proto-plus~=1.25
Provides-Extra: legacy
Requires-Dist: blueye.legacyprotocol>=0.1; extra == "legacy"
Dynamic: license-file
